LICENSE
MANIFEST.in
README.md
setup.cfg
setup.py
corva_welleng.egg-info/PKG-INFO
corva_welleng.egg-info/SOURCES.txt
corva_welleng.egg-info/dependency_links.txt
corva_welleng.egg-info/requires.txt
corva_welleng.egg-info/top_level.txt
welleng/__init__.py
welleng/architecture.py
welleng/clearance.py
welleng/connector.py
welleng/error.py
welleng/fluid.py
welleng/io.py
welleng/mesh.py
welleng/mesh_clearance.py
welleng/node.py
welleng/survey.py
welleng/target.py
welleng/torque_drag.py
welleng/units.py
welleng/utils.py
welleng/version.py
welleng/visual.py
welleng/error_formula_extractor/__init__.py
welleng/error_formula_extractor/enums.py
welleng/error_formula_extractor/formula_extractor.py
welleng/error_formula_extractor/formula_utils.py
welleng/error_formula_extractor/models.py
welleng/errors/__init__.py
welleng/errors/extract_iscwsa_codes.py
welleng/errors/extract_owsg_codes_generic.py
welleng/errors/iscwsa_mwd.py
welleng/errors/singularity_util.py
welleng/errors/tool_errors.py
welleng/errors/tool_index.yaml
welleng/errors/tool_codes/A001Mc.yaml
welleng/errors/tool_codes/A001Mc_Fl.yaml
welleng/errors/tool_codes/A002Mc.yaml
welleng/errors/tool_codes/A002Mc_Fl.yaml
welleng/errors/tool_codes/A003Mc.yaml
welleng/errors/tool_codes/A003Mc_Fl.yaml
welleng/errors/tool_codes/A004Mc.yaml
welleng/errors/tool_codes/A004Mc_Fl.yaml
welleng/errors/tool_codes/A005Mc.yaml
welleng/errors/tool_codes/A005Mc_Fl.yaml
welleng/errors/tool_codes/A006Mc.yaml
welleng/errors/tool_codes/A006Mc_Fl.yaml
welleng/errors/tool_codes/A007Mc.yaml
welleng/errors/tool_codes/A007Mc_Fl.yaml
welleng/errors/tool_codes/A008Mc.yaml
welleng/errors/tool_codes/A008Mc_Fl.yaml
welleng/errors/tool_codes/A009Mc.yaml
welleng/errors/tool_codes/A009Mc_Fl.yaml
welleng/errors/tool_codes/A010Mc.yaml
welleng/errors/tool_codes/A010Mc_Fl.yaml
welleng/errors/tool_codes/A011Mc.yaml
welleng/errors/tool_codes/A011Mc_Fl.yaml
welleng/errors/tool_codes/A012Mc.yaml
welleng/errors/tool_codes/A012Mc_Fl.yaml
welleng/errors/tool_codes/A013Mc.yaml
welleng/errors/tool_codes/A013Mc_Fl.yaml
welleng/errors/tool_codes/A014Mc.yaml
welleng/errors/tool_codes/A014Mc_Fl.yaml
welleng/errors/tool_codes/A015Mc.yaml
