Metadata-Version: 2.1
Name: corva-welleng
Version: 0.5.2
Summary: A collection of Well Engineering tools
Home-page: https://github.com/corva-ai/welleng
Author: Mo Kamyab
Author-email: m.kamyab@corva.ai
License: Apache 2.0
Keywords: well,trajectory,wellpath,wellbore,drilling,drill,error,separation,minimum curvature,iscwsa,owsg,well engineering,wells,drilling engineering,directional drilling,mwd,survey,covariance,digitalization,automation,volve,witsml
Platform: UNKNOWN
Classifier: Development Status :: 4 - Beta
Classifier: License :: OSI Approved :: Apache Software License
Classifier: Programming Language :: Python :: 3.8
Classifier: Natural Language :: English
Classifier: Topic :: Scientific/Engineering
Requires-Python: >=3.8.*
Provides-Extra: easy
Provides-Extra: all
